printeffect/__init__.py
printeffect/inputeffect.py
printeffect/printeffect.py
printeffect-0.1.1.dist-info/METADATA
printeffect-0.1.1.dist-info/WHEEL
printeffect-0.1.1.dist-info/top_level.txt
printeffect-0.1.1.dist-info/RECORD
